local_tuya/__init__.py
local_tuya/__main__.py
local_tuya/backoff.py
local_tuya/config.py
local_tuya/contrib/__init__.py
local_tuya/contrib/airton_ac.py
local_tuya/contrib/ceiling_fan.py
local_tuya/contrib/config.py
local_tuya/dependencies.py
local_tuya/device/README.md
local_tuya/device/__init__.py
local_tuya/device/buffer.py
local_tuya/device/config.py
local_tuya/device/constraints.py
local_tuya/device/device.py
local_tuya/device/state.py
local_tuya/device/value_processors.py
local_tuya/errors.py
local_tuya/events.py
local_tuya/manager.py
local_tuya/mqtt/__init__.py
local_tuya/mqtt/client.py
local_tuya/mqtt/config.py
local_tuya/mqtt/dependencies.py
local_tuya/mqtt/discovery.py
local_tuya/protocol.py
local_tuya/py.typed
local_tuya/tuya/README.md
local_tuya/tuya/__init__.py
local_tuya/tuya/config.py
local_tuya/tuya/dependencies.py
local_tuya/tuya/events.py
local_tuya/tuya/heartbeat.py
local_tuya/tuya/message/__init__.py
local_tuya/tuya/message/handlers/__init__.py
local_tuya/tuya/message/handlers/crypto.py
local_tuya/tuya/message/handlers/handler.py
local_tuya/tuya/message/handlers/v33.py
local_tuya/tuya/message/messages.py
local_tuya/tuya/protocol.py
local_tuya/tuya/receiver.py
local_tuya/tuya/sender.py
local_tuya/tuya/state.py
local_tuya/tuya/transport.py
local_tuya-4.1.0.dist-info/licenses/LICENSE
local_tuya-4.1.0.dist-info/WHEEL
local_tuya-4.1.0.dist-info/METADATA
local_tuya-4.1.0.dist-info/RECORD
