Metadata-Version: 2.4
Name: local-tuya
Version: 4.1.0
Summary: Control Tuya devices with MQTT over LAN.
Author: Gabriel Pajot
Author-email: Gabriel Pajot <gab@lescactus.eu>
License-Expression: MIT
License-File: LICENSE
Requires-Dist: aiomqtt>=2.3.0,<3 ; python_full_version < '4'
Requires-Dist: concurrent-tasks>=1.15.1,<2
Requires-Dist: imbue>=2.1.1,<3
Requires-Dist: pycryptodomex>=3,<4
Requires-Dist: typing-extensions>=4.10
Requires-Dist: zenconfig[pydantic,yaml]>=2.1.1,<3
Requires-Python: >=3.9
Project-URL: repository, https://github.com/gpajot/local-tuya
